officy/__init__.py
officy/celllines.py
officy/csvfile.py
officy/imgfile.py
officy/ipynbfile.py
officy/jsonfile.py
officy/jsonlist.py
officy/mdfile.py
officy/mydir.py
officy/myfile.py
officy/scrawler.py
officy/stime.py
officy/urlfuns.py
officy-0.0.2.dist-info/LICENSE
officy-0.0.2.dist-info/METADATA
officy-0.0.2.dist-info/WHEEL
officy-0.0.2.dist-info/top_level.txt
officy-0.0.2.dist-info/RECORD
