Metadata-Version: 2.1
Name: officy
Version: 0.0.2
Summary: common python code for office use. like dir,file,etc.
Home-page: https://github.com/liujuanjuan1984/officy
Author: liujuanjuan1984
Author-email: qiaoanlu@163.com
License: UNKNOWN
Project-URL: Github Repo, https://github.com/liujuanjuan1984/officy
Project-URL: Bug Tracker, https://github.com/liujuanjuan1984/officy/issues
Keywords: office
Platform: UNKNOWN
Classifier: Programming Language :: Python :: 3
Classifier: License :: OSI Approved :: MIT License
Classifier: Operating System :: OS Independent
Requires-Python: >=3.6
License-File: LICENSE
